langchain_arcade/__init__.py
langchain_arcade/_utilities.py
langchain_arcade/manager.py
langchain_arcade/py.typed
langchain_arcade-1.4.4.dist-info/METADATA
langchain_arcade-1.4.4.dist-info/WHEEL
langchain_arcade-1.4.4.dist-info/licenses/LICENSE
langchain_arcade-1.4.4.dist-info/RECORD
