Metadata-Version: 2.4
Name: langchain-arcade
Version: 1.4.4
Summary: An integration package connecting Arcade and Langchain/LangGraph
License-Expression: MIT
License-File: LICENSE
Requires-Python: >=3.10
Requires-Dist: arcadepy>=1.7.0
Requires-Dist: langchain-core<0.4,>=0.3.49
Provides-Extra: dev
Requires-Dist: langgraph<0.4,>=0.3.23; extra == 'dev'
Requires-Dist: mypy<1.6.0,>=1.5.1; extra == 'dev'
Requires-Dist: pre-commit<3.5.0,>=3.4.0; extra == 'dev'
Requires-Dist: pytest-asyncio<0.25.0,>=0.24.0; extra == 'dev'
Requires-Dist: pytest-cov<4.1.0,>=4.0.0; extra == 'dev'
Requires-Dist: pytest-mock<3.12.0,>=3.11.1; extra == 'dev'
Requires-Dist: pytest<8.4.0,>=8.3.0; extra == 'dev'
Requires-Dist: ruff<0.8.0,>=0.7.4; extra == 'dev'
